wave_share_4d3inch_epaper/__init__.py
wave_share_4d3inch_epaper/wave_share_4d3inch_epaper_uart_module.py
wave_share_4d3inch_epaper-1.0.4.dist-info/LICENSE
wave_share_4d3inch_epaper-1.0.4.dist-info/METADATA
wave_share_4d3inch_epaper-1.0.4.dist-info/WHEEL
wave_share_4d3inch_epaper-1.0.4.dist-info/top_level.txt
wave_share_4d3inch_epaper-1.0.4.dist-info/RECORD
