Metadata-Version: 2.1
Name: wave-share-4d3inch-epaper
Version: 1.0.4
Summary: For WaveShare 4.3inch e-paper UART module.
Home-page: https://github.com/neoctobers/wave_share_4.3inch_epaper
Author: @neoctobers
Author-email: neoctobers@gmail.com
License: UNKNOWN
Platform: UNKNOWN
Classifier: Programming Language :: Python :: 3
Classifier: License :: OSI Approved :: MIT License
Classifier: Operating System :: OS Independent
